ezflix/__init__.py
ezflix/__main__.py
ezflix/__version__.py
ezflix/argument_parser.py
ezflix/ezflix.py
ezflix/main.py
ezflix/torrent.py
ezflix/utils.py
ezflix/extractors/__init__.py
ezflix/extractors/eztv.py
ezflix/extractors/yts.py
ezflix-1.6.5.dist-info/LICENSE
ezflix-1.6.5.dist-info/METADATA
ezflix-1.6.5.dist-info/WHEEL
ezflix-1.6.5.dist-info/entry_points.txt
ezflix-1.6.5.dist-info/top_level.txt
ezflix-1.6.5.dist-info/RECORD
