Metadata-Version: 2.1
Name: ezflix
Version: 1.6.5
Summary: Command line utility to search for TV and movie torrents and stream using Peerflix automatically.
Home-page: https://github.com/AnthonyBloomer/ezflix
Author: Anthony Bloomer
Author-email: ant0@protonmail.ch
License: UNKNOWN
Keywords: torrents,streaming,movies,tv,yify,eztv,peerflix
Platform: UNKNOWN
Classifier: Development Status :: 5 - Production/Stable
Classifier: Environment :: Console
Classifier: Intended Audience :: Developers
Classifier: Intended Audience :: End Users/Desktop
Classifier: Operating System :: OS Independent
Classifier: License :: OSI Approved :: MIT License
Classifier: Programming Language :: Python
Classifier: Programming Language :: Python :: 3.6
Classifier: Programming Language :: Python :: 3.8
Requires-Dist: beautifulsoup4
Requires-Dist: requests
Requires-Dist: colorful
Requires-Dist: subliminal
Requires-Dist: halo
Requires-Dist: PTable
Requires-Dist: future
Requires-Dist: tmdbv3api
